Metadata-Version: 2.4
Name: ggraph
Version: 0.0.1
Summary: Python interface engine and graph definition language for GGUF-based models.
Author-email: Alex O'Connell <git@alexoconnell.net>
License-Expression: MIT
Project-URL: Homepage, https://github.com/acon96/ggraph.py
Project-URL: Repository, https://github.com/acon96/ggraph.py
Requires-Python: >=3.8
License-File: LICENSE
Requires-Dist: numpy>=2.2.6
Requires-Dist: tokenizers>=0.21.1
Requires-Dist: jinja2>=3.1.6
Requires-Dist: lark>=1.2.2
Requires-Dist: matplotlib
Requires-Dist: gguf>=0.17.0
Provides-Extra: gen
Requires-Dist: ctypeslib2-ggml==0.0.1; extra == "gen"
Requires-Dist: clang==14; extra == "gen"
Dynamic: license-file
